Metadata-Version: 2.1
Name: odoo-addon-mrp_planned_order_matrix
Version: 17.0.1.0.0.2
Requires-Python: >=3.10
Requires-Dist: odoo-addon-date_range>=17.0dev,<17.1dev
Requires-Dist: odoo-addon-mrp_multi_level>=17.0dev,<17.1dev
Requires-Dist: odoo-addon-web_widget_x2many_2d_matrix>=17.0dev,<17.1dev
Requires-Dist: odoo>=17.0a,<17.1dev
Summary: Allows to create fixed planned orders on a grid view.
Home-page: https://github.com/OCA/manufacture
License: AGPL-3
Author: ForgeFlow, Odoo Community Association (OCA)
Author-email: support@odoo-community.org
Classifier: Programming Language :: Python
Classifier: Framework :: Odoo
Classifier: Framework :: Odoo :: 17.0
Classifier: License :: OSI Approved :: GNU Affero General Public License v3
Classifier: Development Status :: 5 - Production/Stable
